superdate/SuperDate.py
superdate/__init__.py
superdate/parse_date.py
superdate-0.2.2.dist-info/licenses/LICENSE
superdate-0.2.2.dist-info/METADATA
superdate-0.2.2.dist-info/WHEEL
superdate-0.2.2.dist-info/top_level.txt
superdate-0.2.2.dist-info/RECORD
