Metadata-Version: 2.4
Name: superdate
Version: 0.2.2
Summary: A super flexible and performant date parser.
Author-email: Raven <raven@rubicon.aleeas.com>
License-Expression: GPL-2.0
Project-URL: Homepage, https://github.com/digital-raven/superdate
Requires-Python: <4,>=3
License-File: LICENSE
Requires-Dist: parsedatetime<3
Dynamic: license-file
